MANIFEST.in
l10n_be_hr_payroll_data.xml
l10n_be_hr_payroll_demo.xml
l10n_be_hr_payroll_view.xml
setup.py
./__init__.py
./__openerp__.py
./l10n_be_hr_payroll.py
data/hr.salary.rule.csv
i18n/de.po
i18n/es.po
i18n/es_CR.po
i18n/l10n_be_hr_payroll.pot
i18n/nl.po
i18n/pt.po
i18n/pt_BR.po
i18n/sl.po
i18n/sr@latin.po
i18n/tr.po
i18n/zh_CN.po
openerp_l10n_be_hr_payroll.egg-info/PKG-INFO
openerp_l10n_be_hr_payroll.egg-info/SOURCES.txt
openerp_l10n_be_hr_payroll.egg-info/dependency_links.txt
openerp_l10n_be_hr_payroll.egg-info/requires.txt
openerp_l10n_be_hr_payroll.egg-info/top_level.txt
static/src/img/icon.png